{"trial_id": "45", "hyperparameters": {"space": [{"class_name": "Int", "config": {"name": "num_layers", "default": null, "conditions": [], "min_value": 1, "max_value": 3, "step": 1, "sampling": "linear"}}, {"class_name": "Int", "config": {"name": "units_0", "default": null, "conditions": [], "min_value": 32, "max_value": 512, "step": 32, "sampling": "linear"}}, {"class_name": "Choice", "config": {"name": "activation_0", "default": "relu", "conditions": [], "values": ["relu", "tanh", "elu"], "ordered": false}}, {"class_name": "Boolean", "config": {"name": "batch_norm_0", "default": false, "conditions": []}}, {"class_name": "Float", "config": {"name": "dropout_0", "default": 0.0, "conditions": [], "min_value": 0.0, "max_value": 0.5, "step": 0.1, "sampling": "linear"}}, {"class_name": "Float", "config": {"name": "learning_rate", "default": 0.0001, "conditions": [], "min_value": 0.0001, "max_value": 0.01, "step": null, "sampling": "log"}}, {"class_name": "Int", "config": {"name": "units_1", "default": null, "conditions": [], "min_value": 32, "max_value": 512, "step": 32, "sampling": "linear"}}, {"class_name": "Choice", "config": {"name": "activation_1", "default": "relu", "conditions": [], "values": ["relu", "tanh", "elu"], "ordered": false}}, {"class_name": "Boolean", "config": {"name": "batch_norm_1", "default": false, "conditions": []}}, {"class_name": "Float", "config": {"name": "dropout_1", "default": 0.0, "conditions": [], "min_value": 0.0, "max_value": 0.5, "step": 0.1, "sampling": "linear"}}, {"class_name": "Int", "config": {"name": "units_2", "default": null, "conditions": [], "min_value": 32, "max_value": 512, "step": 32, "sampling": "linear"}}, {"class_name": "Choice", "config": {"name": "activation_2", "default": "relu", "conditions": [], "values": ["relu", "tanh", "elu"], "ordered": false}}, {"class_name": "Boolean", "config": {"name": "batch_norm_2", "default": false, "conditions": []}}, {"class_name": "Float", "config": {"name": "dropout_2", "default": 0.0, "conditions": [], "min_value": 0.0, "max_value": 0.5, "step": 0.1, "sampling": "linear"}}], "values": {"num_layers": 3, "units_0": 352, "activation_0": "tanh", "batch_norm_0": true, "dropout_0": 0.0, "learning_rate": 0.00035246987335309373, "units_1": 32, "activation_1": "relu", "batch_norm_1": true, "dropout_1": 0.30000000000000004, "units_2": 64, "activation_2": "elu", "batch_norm_2": false, "dropout_2": 0.1}}, "metrics": {"metrics": {"accuracy": {"direction": "max", "observations": [{"value": [0.6171761453151703], "step": 42}]}, "loss": {"direction": "min", "observations": [{"value": [0.9825154542922974], "step": 42}]}, "val_accuracy": {"direction": "max", "observations": [{"value": [0.6831395328044891], "step": 42}]}, "val_loss": {"direction": "min", "observations": [{"value": [0.947073757648468], "step": 42}]}}}, "score": 0.6831395328044891, "best_step": 42, "status": "COMPLETED", "message": null}